CHANGES.txt
DEPENDENCES.txt
README.txt
setup.py
src/__init__.py
src/ng/__init__.py
src/ng.content.location.egg-info/PKG-INFO
src/ng.content.location.egg-info/SOURCES.txt
src/ng.content.location.egg-info/dependency_links.txt
src/ng.content.location.egg-info/namespace_packages.txt
src/ng.content.location.egg-info/not-zip-safe
src/ng.content.location.egg-info/requires.txt
src/ng.content.location.egg-info/top_level.txt
src/ng/content/__init__.py
src/ng/content/location/__init__.py
src/ng/content/location/configure.zcml
src/ng/content/location/geolocationadapter.py
src/ng/content/location/interfaces.py
src/ng/content/location/locationannotation.py
src/ng/content/location/locationannotationableadapter.py
src/ng/content/location/ng.content.location.txt
src/ng/content/location/browser/__init__.py
src/ng/content/location/browser/configure.zcml
src/ng/content/location/browser/viewlocationannotation.pt
src/ng/content/location/browser/viewlocationannotation.py
src/ng/content/location/etc/ng.content.location-configure.zcml